emoji.py
workspace.py
wsp.py
pathify-0.1.2.dist-info/METADATA
pathify-0.1.2.dist-info/WHEEL
pathify-0.1.2.dist-info/entry_points.txt
pathify-0.1.2.dist-info/top_level.txt
pathify-0.1.2.dist-info/RECORD
